asrank/__init__.py
asrank/asrank.py
asrank/test_asrank.py
pyasrank-0.1.1.dist-info/LICENSE
pyasrank-0.1.1.dist-info/METADATA
pyasrank-0.1.1.dist-info/WHEEL
pyasrank-0.1.1.dist-info/top_level.txt
pyasrank-0.1.1.dist-info/RECORD
